IM_COOL_BOOY_FM/__init__.py
IM_COOL_BOOY_FM/__main__.py
IM_COOL_BOOY_FM/cli_tool.py
IM_COOL_BOOY_FM/init.py
IM_COOL_BOOY_FM/main.py
im_cool_booy_fm-1.2.1.dist-info/licenses/LICENSE
im_cool_booy_fm-1.2.1.dist-info/METADATA
im_cool_booy_fm-1.2.1.dist-info/WHEEL
im_cool_booy_fm-1.2.1.dist-info/entry_points.txt
im_cool_booy_fm-1.2.1.dist-info/top_level.txt
im_cool_booy_fm-1.2.1.dist-info/RECORD
