Metadata-Version: 2.4
Name: IM-COOL-BOOY-FM
Version: 1.2.1
Summary: A colorful and powerful CLI tool to search, play, and manage your favorite radio stations worldwide.
Author: IM COOL BOOY
Author-email: coolbooy@gmail.com
License: MIT
Keywords: FM
Classifier: Programming Language :: Python :: 3
Classifier: License :: OSI Approved :: MIT License
Classifier: Operating System :: OS Independent
Requires-Python: >=3.6
License-File: LICENSE
Requires-Dist: requests>=2.25.0
Requires-Dist: python-vlc>=3.0.1115
Requires-Dist: colorama>=0.4.4
Dynamic: author
Dynamic: author-email
Dynamic: classifier
Dynamic: description
Dynamic: description-content-type
Dynamic: keywords
Dynamic: license-file
Dynamic: requires-dist
Dynamic: requires-python
Dynamic: summary
